txs/__init__.py
txs/ffmpeg.py
txs/main.py
txs/utils.py
txs-0.1.3.data/data/share/txs/lua/txs-compare.lua
txs-0.1.3.dist-info/METADATA
txs-0.1.3.dist-info/WHEEL
txs-0.1.3.dist-info/entry_points.txt
txs-0.1.3.dist-info/top_level.txt
txs-0.1.3.dist-info/RECORD
