Metadata-Version: 2.1
Name: txs
Version: 0.1.3
Summary: Wrapper around ffmpeg and mpv that generates and compares x264 test encodes
Home-page: http://github.com/plotski/txs
Author: plotski
Author-email: plotski@example.org
License: GPLv3
Platform: UNKNOWN
Classifier: Programming Language :: Python :: 3
Classifier: License :: OSI Approved :: GNU General Public License v3 or later (GPLv3+)
Requires-Python: >=3.6
